django_restrictmethodorigin-0.1.1.dist-info/DESCRIPTION.rst
django_restrictmethodorigin-0.1.1.dist-info/METADATA
django_restrictmethodorigin-0.1.1.dist-info/RECORD
django_restrictmethodorigin-0.1.1.dist-info/WHEEL
django_restrictmethodorigin-0.1.1.dist-info/metadata.json
django_restrictmethodorigin-0.1.1.dist-info/top_level.txt
restrictmethodorigin/__init__.py
restrictmethodorigin/apps.py
restrictmethodorigin/base.py
